{
  "checkpoint": "/root/autodl-tmp/micro/experiments/v20_object_joint_medium10/checkpoints/latest_v19_object_joint.pt",
  "real_afm_roots": [
    "/root/autodl-tmp/micro/real_afm/edafm_sup03_cases",
    "/root/autodl-tmp/micro/real_afm/camphor_sup03_cases"
  ],
  "edafm_root": "/root/autodl-tmp/real_afm_datasets/edafm_zenodo_10609676/edafm-data/edafm-data",
  "camphor_structure_root": "/root/autodl-tmp/real_afm_datasets/camphor_adsorbate_4710346/structures",
  "candidate_count": 10,
  "candidate_labels": [
    "BCB",
    "NCM",
    "PTCDA",
    "PTH",
    "TTF-TDZ",
    "Water",
    "camphor"
  ],
  "candidate_names": [
    "BCB",
    "NCM",
    "PTCDA",
    "PTH",
    "TTF-TDZ",
    "Water",
    "camphor_A1",
    "camphor_A2",
    "camphor_A3",
    "camphor_A4"
  ],
  "normal": {
    "checkpoint": "/root/autodl-tmp/micro/experiments/v20_object_joint_medium10/checkpoints/latest_v19_object_joint.pt",
    "contrast_variant": "normal",
    "candidate_count": 10,
    "candidate_labels": [
      "BCB",
      "NCM",
      "PTCDA",
      "PTH",
      "TTF-TDZ",
      "Water",
      "camphor"
    ],
    "candidate_names": [
      "BCB",
      "NCM",
      "PTCDA",
      "PTH",
      "TTF-TDZ",
      "Water",
      "camphor_A1",
      "camphor_A2",
      "camphor_A3",
      "camphor_A4"
    ],
    "retrieval_all_cases": {
      "num_cases": 11,
      "top1": 0.09090909090909091,
      "top3": 0.18181818181818182,
      "top5": 0.2727272727272727,
      "mrr": 0.2738095238095238,
      "mean_rank": 5.2727272727272725
    },
    "retrieval_gt_compatible_subset": {
      "num_cases": 4,
      "top1": 0.25,
      "top3": 0.5,
      "top5": 0.75,
      "mrr": 0.47916666666666663,
      "mean_rank": 3.25
    },
    "gt_metric_subset": {
      "num_cases": 4,
      "mean_pred_object_score": 0.41692799424345306,
      "mean_pred_object_3d_score": 0.5385315407000042,
      "mean_pred_object_count_mae": 23.0,
      "mean_pred_object_type_acc": 0.5888157894736842,
      "mean_pred_object_macro_f1": 0.18730347976249617,
      "mean_pred_object_hetero_f1": 0.11538461538461536,
      "mean_pred_object_edge_f1": 0.45232181379984493,
      "mean_pred_object_edge_f1_robust": 0.125,
      "mean_pred_object_match_coverage_robust": 0.1381578947368421,
      "mean_pred_object_heavy_rmsd": 0.30410210229456425,
      "mean_pred_object_z_mae": 0.12635111808776855,
      "mean_center_score": 0.9273259170974294
    },
    "records": [
      {
        "case_id": "edafm_BCB_CO_exp",
        "molecule_name": "BCB",
        "molecule_label": "BCB",
        "tip": "CO",
        "contrast_variant": "normal",
        "gt_structure_compatible": true,
        "gt_rank": 6,
        "reciprocal_rank": 0.16666666666666666,
        "top1_hit": false,
        "top3_hit": false,
        "top5_hit": false,
        "top1_label": "Water",
        "top1_candidate_name": "Water",
        "top1_sim": 0.32471056054940506,
        "top3_labels": [
          "Water",
          "PTH",
          "TTF-TDZ"
        ],
        "top3_candidate_names": [
          "Water",
          "PTH",
          "TTF-TDZ"
        ],
        "top3_sims": [
          0.32471056054940506,
          0.313595245754595,
          0.31247526520733276
        ],
        "gt_atom_count": 12,
        "pred_atom_count": 48,
        "pred_object_score": 0.22009001750240983,
        "pred_object_3d_score": 0.48164300241818025,
        "pred_object_count_mae": 36.0,
        "pred_object_type_acc": 0.25,
        "pred_object_macro_f1": 0.01948051948051948,
        "pred_object_hetero_f1": 0.0,
        "pred_object_edge_f1": 0.37499999999999994,
        "pred_object_edge_f1_robust": 0.0,
        "pred_object_match_coverage_robust": 0.08333333333333333,
        "pred_object_heavy_rmsd": 0.1973281353712082,
        "pred_object_z_mae": 0.1548638790845871,
        "mean_center_score": 0.8238782721261183,
        "figure_path": "/root/autodl-tmp/micro/experiments/v20_object_joint_medium10_sup03_real_afm_expanded/figures/normal/edafm_BCB_CO_exp.png",
        "compar_figure_path": "/root/autodl-tmp/micro/experiments/v20_object_joint_medium10_sup03_real_afm_expanded/comparisons/normal/edafm_BCB_CO_exp.png"
      },
      {
        "case_id": "edafm_BCB_Xe_exp",
        "molecule_name": "BCB",
        "molecule_label": "BCB",
        "tip": "Xe",
        "contrast_variant": "normal",
        "gt_structure_compatible": true,
        "gt_rank": 4,
        "reciprocal_rank": 0.25,
        "top1_hit": false,
        "top3_hit": false,
        "top5_hit": true,
        "top1_label": "PTH",
        "top1_candidate_name": "PTH",
        "top1_sim": 0.6471208314417065,
        "top3_labels": [
          "PTH",
          "NCM",
          "TTF-TDZ"
        ],
        "top3_candidate_names": [
          "PTH",
          "NCM",
          "TTF-TDZ"
        ],
        "top3_sims": [
          0.6471208314417065,
          0.6358307755821919,
          0.6321696428778748
        ],
        "gt_atom_count": 12,
        "pred_atom_count": 48,
        "pred_object_score": 0.5443340320580384,
        "pred_object_3d_score": 0.793294812315567,
        "pred_object_count_mae": 36.0,
        "pred_object_type_acc": 1.0,
        "pred_object_macro_f1": 0.4,
        "pred_object_hetero_f1": 0.0,
        "pred_object_edge_f1": 0.6363636363636364,
        "pred_object_edge_f1_robust": 0.5,
        "pred_object_match_coverage_robust": 0.4166666666666667,
        "pred_object_heavy_rmsd": 0.06594588607549667,
        "pred_object_z_mae": 0.05387575924396515,
        "mean_center_score": 0.9912260957062244,
        "figure_path": "/root/autodl-tmp/micro/experiments/v20_object_joint_medium10_sup03_real_afm_expanded/figures/normal/edafm_BCB_Xe_exp.png",
        "compar_figure_path": "/root/autodl-tmp/micro/experiments/v20_object_joint_medium10_sup03_real_afm_expanded/comparisons/normal/edafm_BCB_Xe_exp.png"
      },
      {
        "case_id": "edafm_PTCDA_CO_exp",
        "molecule_name": "PTCDA",
        "molecule_label": "PTCDA",
        "tip": "CO",
        "contrast_variant": "normal",
        "gt_structure_compatible": true,
        "gt_rank": 1,
        "reciprocal_rank": 1.0,
        "top1_hit": true,
        "top3_hit": true,
        "top5_hit": true,
        "top1_label": "PTCDA",
        "top1_candidate_name": "PTCDA",
        "top1_sim": 0.254453228576743,
        "top3_labels": [
          "PTCDA",
          "PTH",
          "NCM"
        ],
        "top3_candidate_names": [
          "PTCDA",
          "PTH",
          "NCM"
        ],
        "top3_sims": [
          0.254453228576743,
          0.2287559523809524,
          0.2271280502250652
        ],
        "gt_atom_count": 38,
        "pred_atom_count": 48,
        "pred_object_score": 0.4336510621899399,
        "pred_object_3d_score": 0.43314952468462653,
        "pred_object_count_mae": 10.0,
        "pred_object_type_acc": 0.5263157894736842,
        "pred_object_macro_f1": 0.12525252525252525,
        "pred_object_hetero_f1": 0.15384615384615383,
        "pred_object_edge_f1": 0.4301075268817204,
        "pred_object_edge_f1_robust": 0.0,
        "pred_object_match_coverage_robust": 0.02631578947368421,
        "pred_object_heavy_rmsd": 0.5166571140289307,
        "pred_object_z_mae": 0.19326910376548767,
        "mean_center_score": 0.9834636263549328,
        "figure_path": "/root/autodl-tmp/micro/experiments/v20_object_joint_medium10_sup03_real_afm_expanded/figures/normal/edafm_PTCDA_CO_exp.png",
        "compar_figure_path": "/root/autodl-tmp/micro/experiments/v20_object_joint_medium10_sup03_real_afm_expanded/comparisons/normal/edafm_PTCDA_CO_exp.png"
      },
      {
        "case_id": "edafm_PTCDA_Xe_exp",
        "molecule_name": "PTCDA",
        "molecule_label": "PTCDA",
        "tip": "Xe",
        "contrast_variant": "normal",
        "gt_structure_compatible": true,
        "gt_rank": 2,
        "reciprocal_rank": 0.5,
        "top1_hit": false,
        "top3_hit": true,
        "top5_hit": true,
        "top1_label": "Water",
        "top1_candidate_name": "Water",
        "top1_sim": 0.30256823255375087,
        "top3_labels": [
          "Water",
          "PTCDA",
          "NCM"
        ],
        "top3_candidate_names": [
          "Water",
          "PTCDA",
          "NCM"
        ],
        "top3_sims": [
          0.30256823255375087,
          0.282198784318931,
          0.2754099135263519
        ],
        "gt_atom_count": 38,
        "pred_atom_count": 48,
        "pred_object_score": 0.469636865223424,
        "pred_object_3d_score": 0.44603882338164325,
        "pred_object_count_mae": 10.0,
        "pred_object_type_acc": 0.5789473684210527,
        "pred_object_macro_f1": 0.2044808743169399,
        "pred_object_hetero_f1": 0.30769230769230765,
        "pred_object_edge_f1": 0.367816091954023,
        "pred_object_edge_f1_robust": 0.0,
        "pred_object_match_coverage_robust": 0.02631578947368421,
        "pred_object_heavy_rmsd": 0.43647727370262146,
        "pred_object_z_mae": 0.1033957302570343,
        "mean_center_score": 0.9107356742024422,
        "figure_path": "/root/autodl-tmp/micro/experiments/v20_object_joint_medium10_sup03_real_afm_expanded/figures/normal/edafm_PTCDA_Xe_exp.png",
        "compar_figure_path": "/root/autodl-tmp/micro/experiments/v20_object_joint_medium10_sup03_real_afm_expanded/comparisons/normal/edafm_PTCDA_Xe_exp.png"
      },
      {
        "case_id": "edafm_Water_CO_exp",
        "molecule_name": "Water",
        "molecule_label": "Water",
        "tip": "CO",
        "contrast_variant": "normal",
        "gt_structure_compatible": false,
        "gt_rank": 7,
        "reciprocal_rank": 0.14285714285714285,
        "top1_hit": false,
        "top3_hit": false,
        "top5_hit": false,
        "top1_label": "BCB",
        "top1_candidate_name": "BCB",
        "top1_sim": 0.6192460381558963,
        "top3_labels": [
          "BCB",
          "TTF-TDZ",
          "PTH"
        ],
        "top3_candidate_names": [
          "BCB",
          "TTF-TDZ",
          "PTH"
        ],
        "top3_sims": [
          0.6192460381558963,
          0.549024168756154,
          0.5350347218416266
        ],
        "gt_atom_count": null,
        "pred_atom_count": 48,
        "pred_object_score": null,
        "pred_object_3d_score": null,
        "pred_object_count_mae": null,
        "pred_object_type_acc": null,
        "pred_object_macro_f1": null,
        "pred_object_hetero_f1": null,
        "pred_object_edge_f1": null,
        "pred_object_edge_f1_robust": null,
        "pred_object_match_coverage_robust": null,
        "pred_object_heavy_rmsd": null,
        "pred_object_z_mae": null,
        "mean_center_score": 0.7658891859464347,
        "figure_path": "/root/autodl-tmp/micro/experiments/v20_object_joint_medium10_sup03_real_afm_expanded/figures/normal/edafm_Water_CO_exp.png",
        "compar_figure_path": "/root/autodl-tmp/micro/experiments/v20_object_joint_medium10_sup03_real_afm_expanded/comparisons/normal/edafm_Water_CO_exp.png"
      },
      {
        "case_id": "edafm_Water_Xe_exp",
        "molecule_name": "Water",
        "molecule_label": "Water",
        "tip": "Xe",
        "contrast_variant": "normal",
        "gt_structure_compatible": false,
        "gt_rank": 6,
        "reciprocal_rank": 0.16666666666666666,
        "top1_hit": false,
        "top3_hit": false,
        "top5_hit": false,
        "top1_label": "TTF-TDZ",
        "top1_candidate_name": "TTF-TDZ",
        "top1_sim": 0.6560365955703747,
        "top3_labels": [
          "TTF-TDZ",
          "BCB",
          "NCM"
        ],
        "top3_candidate_names": [
          "TTF-TDZ",
          "BCB",
          "NCM"
        ],
        "top3_sims": [
          0.6560365955703747,
          0.6546768928464356,
          0.6413639800079879
        ],
        "gt_atom_count": null,
        "pred_atom_count": 48,
        "pred_object_score": null,
        "pred_object_3d_score": null,
        "pred_object_count_mae": null,
        "pred_object_type_acc": null,
        "pred_object_macro_f1": null,
        "pred_object_hetero_f1": null,
        "pred_object_edge_f1": null,
        "pred_object_edge_f1_robust": null,
        "pred_object_match_coverage_robust": null,
        "pred_object_heavy_rmsd": null,
        "pred_object_z_mae": null,
        "mean_center_score": 0.9014904623230299,
        "figure_path": "/root/autodl-tmp/micro/experiments/v20_object_joint_medium10_sup03_real_afm_expanded/figures/normal/edafm_Water_Xe_exp.png",
        "compar_figure_path": "/root/autodl-tmp/micro/experiments/v20_object_joint_medium10_sup03_real_afm_expanded/comparisons/normal/edafm_Water_Xe_exp.png"
      },
      {
        "case_id": "camphor_exp_1",
        "molecule_name": "camphor",
        "molecule_label": "camphor",
        "tip": "unknown",
        "contrast_variant": "normal",
        "gt_structure_compatible": false,
        "gt_rank": 6,
        "reciprocal_rank": 0.16666666666666666,
        "top1_hit": false,
        "top3_hit": false,
        "top5_hit": false,
        "top1_label": "PTCDA",
        "top1_candidate_name": "PTCDA",
        "top1_sim": 0.39519690083531206,
        "top3_labels": [
          "PTCDA",
          "PTH",
          "TTF-TDZ"
        ],
        "top3_candidate_names": [
          "PTCDA",
          "PTH",
          "TTF-TDZ"
        ],
        "top3_sims": [
          0.39519690083531206,
          0.3633190912945877,
          0.3579150072733561
        ],
        "gt_atom_count": null,
        "pred_atom_count": 16,
        "pred_object_score": null,
        "pred_object_3d_score": null,
        "pred_object_count_mae": null,
        "pred_object_type_acc": null,
        "pred_object_macro_f1": null,
        "pred_object_hetero_f1": null,
        "pred_object_edge_f1": null,
        "pred_object_edge_f1_robust": null,
        "pred_object_match_coverage_robust": null,
        "pred_object_heavy_rmsd": null,
        "pred_object_z_mae": null,
        "mean_center_score": 0.9836304411292076,
        "figure_path": "/root/autodl-tmp/micro/experiments/v20_object_joint_medium10_sup03_real_afm_expanded/figures/normal/camphor_exp_1.png",
        "compar_figure_path": "/root/autodl-tmp/micro/experiments/v20_object_joint_medium10_sup03_real_afm_expanded/comparisons/normal/camphor_exp_1.png"
      },
      {
        "case_id": "camphor_exp_3",
        "molecule_name": "camphor",
        "molecule_label": "camphor",
        "tip": "unknown",
        "contrast_variant": "normal",
        "gt_structure_compatible": false,
        "gt_rank": 7,
        "reciprocal_rank": 0.14285714285714285,
        "top1_hit": false,
        "top3_hit": false,
        "top5_hit": false,
        "top1_label": "PTCDA",
        "top1_candidate_name": "PTCDA",
        "top1_sim": 0.4370838492675532,
        "top3_labels": [
          "PTCDA",
          "Water",
          "BCB"
        ],
        "top3_candidate_names": [
          "PTCDA",
          "Water",
          "BCB"
        ],
        "top3_sims": [
          0.4370838492675532,
          0.3586323930963694,
          0.3504195542562576
        ],
        "gt_atom_count": null,
        "pred_atom_count": 16,
        "pred_object_score": null,
        "pred_object_3d_score": null,
        "pred_object_count_mae": null,
        "pred_object_type_acc": null,
        "pred_object_macro_f1": null,
        "pred_object_hetero_f1": null,
        "pred_object_edge_f1": null,
        "pred_object_edge_f1_robust": null,
        "pred_object_match_coverage_robust": null,
        "pred_object_heavy_rmsd": null,
        "pred_object_z_mae": null,
        "mean_center_score": 0.9942876361310482,
        "figure_path": "/root/autodl-tmp/micro/experiments/v20_object_joint_medium10_sup03_real_afm_expanded/figures/normal/camphor_exp_3.png",
        "compar_figure_path": "/root/autodl-tmp/micro/experiments/v20_object_joint_medium10_sup03_real_afm_expanded/comparisons/normal/camphor_exp_3.png"
      },
      {
        "case_id": "camphor_exp_4",
        "molecule_name": "camphor",
        "molecule_label": "camphor",
        "tip": "unknown",
        "contrast_variant": "normal",
        "gt_structure_compatible": false,
        "gt_rank": 6,
        "reciprocal_rank": 0.16666666666666666,
        "top1_hit": false,
        "top3_hit": false,
        "top5_hit": false,
        "top1_label": "TTF-TDZ",
        "top1_candidate_name": "TTF-TDZ",
        "top1_sim": 0.4578521884293948,
        "top3_labels": [
          "TTF-TDZ",
          "BCB",
          "PTH"
        ],
        "top3_candidate_names": [
          "TTF-TDZ",
          "BCB",
          "PTH"
        ],
        "top3_sims": [
          0.4578521884293948,
          0.4558063898520933,
          0.44901436060004757
        ],
        "gt_atom_count": null,
        "pred_atom_count": 18,
        "pred_object_score": null,
        "pred_object_3d_score": null,
        "pred_object_count_mae": null,
        "pred_object_type_acc": null,
        "pred_object_macro_f1": null,
        "pred_object_hetero_f1": null,
        "pred_object_edge_f1": null,
        "pred_object_edge_f1_robust": null,
        "pred_object_match_coverage_robust": null,
        "pred_object_heavy_rmsd": null,
        "pred_object_z_mae": null,
        "mean_center_score": 0.9921888444158766,
        "figure_path": "/root/autodl-tmp/micro/experiments/v20_object_joint_medium10_sup03_real_afm_expanded/figures/normal/camphor_exp_4.png",
        "compar_figure_path": "/root/autodl-tmp/micro/experiments/v20_object_joint_medium10_sup03_real_afm_expanded/comparisons/normal/camphor_exp_4.png"
      },
      {
        "case_id": "camphor_exp_6",
        "molecule_name": "camphor",
        "molecule_label": "camphor",
        "tip": "unknown",
        "contrast_variant": "normal",
        "gt_structure_compatible": false,
        "gt_rank": 7,
        "reciprocal_rank": 0.14285714285714285,
        "top1_hit": false,
        "top3_hit": false,
        "top5_hit": false,
        "top1_label": "PTH",
        "top1_candidate_name": "PTH",
        "top1_sim": 0.4838569948481369,
        "top3_labels": [
          "PTH",
          "TTF-TDZ",
          "NCM"
        ],
        "top3_candidate_names": [
          "PTH",
          "TTF-TDZ",
          "NCM"
        ],
        "top3_sims": [
          0.4838569948481369,
          0.47431554718801594,
          0.4475229723258478
        ],
        "gt_atom_count": null,
        "pred_atom_count": 48,
        "pred_object_score": null,
        "pred_object_3d_score": null,
        "pred_object_count_mae": null,
        "pred_object_type_acc": null,
        "pred_object_macro_f1": null,
        "pred_object_hetero_f1": null,
        "pred_object_edge_f1": null,
        "pred_object_edge_f1_robust": null,
        "pred_object_match_coverage_robust": null,
        "pred_object_heavy_rmsd": null,
        "pred_object_z_mae": null,
        "mean_center_score": 0.9902606916924318,
        "figure_path": "/root/autodl-tmp/micro/experiments/v20_object_joint_medium10_sup03_real_afm_expanded/figures/normal/camphor_exp_6.png",
        "compar_figure_path": "/root/autodl-tmp/micro/experiments/v20_object_joint_medium10_sup03_real_afm_expanded/comparisons/normal/camphor_exp_6.png"
      },
      {
        "case_id": "camphor_exp_7",
        "molecule_name": "camphor",
        "molecule_label": "camphor",
        "tip": "unknown",
        "contrast_variant": "normal",
        "gt_structure_compatible": false,
        "gt_rank": 6,
        "reciprocal_rank": 0.16666666666666666,
        "top1_hit": false,
        "top3_hit": false,
        "top5_hit": false,
        "top1_label": "BCB",
        "top1_candidate_name": "BCB",
        "top1_sim": 0.5502495330937136,
        "top3_labels": [
          "BCB",
          "NCM",
          "PTCDA"
        ],
        "top3_candidate_names": [
          "BCB",
          "NCM",
          "PTCDA"
        ],
        "top3_sims": [
          0.5502495330937136,
          0.47998868934711814,
          0.4720285673372946
        ],
        "gt_atom_count": null,
        "pred_atom_count": 48,
        "pred_object_score": null,
        "pred_object_3d_score": null,
        "pred_object_count_mae": null,
        "pred_object_type_acc": null,
        "pred_object_macro_f1": null,
        "pred_object_hetero_f1": null,
        "pred_object_edge_f1": null,
        "pred_object_edge_f1_robust": null,
        "pred_object_match_coverage_robust": null,
        "pred_object_heavy_rmsd": null,
        "pred_object_z_mae": null,
        "mean_center_score": 0.7695725297089666,
        "figure_path": "/root/autodl-tmp/micro/experiments/v20_object_joint_medium10_sup03_real_afm_expanded/figures/normal/camphor_exp_7.png",
        "compar_figure_path": "/root/autodl-tmp/micro/experiments/v20_object_joint_medium10_sup03_real_afm_expanded/comparisons/normal/camphor_exp_7.png"
      }
    ]
  },
  "inverted": {
    "checkpoint": "/root/autodl-tmp/micro/experiments/v20_object_joint_medium10/checkpoints/latest_v19_object_joint.pt",
    "contrast_variant": "inverted",
    "candidate_count": 10,
    "candidate_labels": [
      "BCB",
      "NCM",
      "PTCDA",
      "PTH",
      "TTF-TDZ",
      "Water",
      "camphor"
    ],
    "candidate_names": [
      "BCB",
      "NCM",
      "PTCDA",
      "PTH",
      "TTF-TDZ",
      "Water",
      "camphor_A1",
      "camphor_A2",
      "camphor_A3",
      "camphor_A4"
    ],
    "retrieval_all_cases": {
      "num_cases": 11,
      "top1": 0.18181818181818182,
      "top3": 0.45454545454545453,
      "top5": 0.7272727272727273,
      "mrr": 0.40541125541125544,
      "mean_rank": 3.8181818181818183
    },
    "retrieval_gt_compatible_subset": {
      "num_cases": 4,
      "top1": 0.5,
      "top3": 0.75,
      "top5": 1.0,
      "mrr": 0.6333333333333334,
      "mean_rank": 2.5
    },
    "gt_metric_subset": {
      "num_cases": 4,
      "mean_pred_object_score": 0.4658867417657634,
      "mean_pred_object_3d_score": 0.682137437280208,
      "mean_pred_object_count_mae": 20.0,
      "mean_pred_object_type_acc": 0.7335526315789473,
      "mean_pred_object_macro_f1": 0.15137705789863115,
      "mean_pred_object_hetero_f1": 0.16538461538461538,
      "mean_pred_object_edge_f1": 0.5030572506476121,
      "mean_pred_object_edge_f1_robust": 0.1,
      "mean_pred_object_match_coverage_robust": 0.1699561403508772,
      "mean_pred_object_heavy_rmsd": 0.13989608734846115,
      "mean_pred_object_z_mae": 0.06589327113033505,
      "mean_center_score": 0.9110805970817132
    },
    "records": [
      {
        "case_id": "edafm_BCB_CO_exp",
        "molecule_name": "BCB",
        "molecule_label": "BCB",
        "tip": "CO",
        "contrast_variant": "inverted",
        "gt_structure_compatible": true,
        "gt_rank": 1,
        "reciprocal_rank": 1.0,
        "top1_hit": true,
        "top3_hit": true,
        "top5_hit": true,
        "top1_label": "BCB",
        "top1_candidate_name": "BCB",
        "top1_sim": 0.5761092199104376,
        "top3_labels": [
          "BCB",
          "TTF-TDZ",
          "PTCDA"
        ],
        "top3_candidate_names": [
          "BCB",
          "TTF-TDZ",
          "PTCDA"
        ],
        "top3_sims": [
          0.5761092199104376,
          0.5241946275974015,
          0.5006001334081279
        ],
        "gt_atom_count": 12,
        "pred_atom_count": 48,
        "pred_object_score": 0.49513686487844366,
        "pred_object_3d_score": 0.7893710613518488,
        "pred_object_count_mae": 36.0,
        "pred_object_type_acc": 1.0,
        "pred_object_macro_f1": 0.22641509433962262,
        "pred_object_hetero_f1": 0.0,
        "pred_object_edge_f1": 0.6,
        "pred_object_edge_f1_robust": 0.0,
        "pred_object_match_coverage_robust": 0.3333333333333333,
        "pred_object_heavy_rmsd": 0.06086643040180206,
        "pred_object_z_mae": 0.03558177128434181,
        "mean_center_score": 0.8470769202103838,
        "figure_path": "/root/autodl-tmp/micro/experiments/v20_object_joint_medium10_sup03_real_afm_expanded/figures/inverted/edafm_BCB_CO_exp.png",
        "compar_figure_path": "/root/autodl-tmp/micro/experiments/v20_object_joint_medium10_sup03_real_afm_expanded/comparisons/inverted/edafm_BCB_CO_exp.png"
      },
      {
        "case_id": "edafm_BCB_Xe_exp",
        "molecule_name": "BCB",
        "molecule_label": "BCB",
        "tip": "Xe",
        "contrast_variant": "inverted",
        "gt_structure_compatible": true,
        "gt_rank": 1,
        "reciprocal_rank": 1.0,
        "top1_hit": true,
        "top3_hit": true,
        "top5_hit": true,
        "top1_label": "BCB",
        "top1_candidate_name": "BCB",
        "top1_sim": 0.37878349003337675,
        "top3_labels": [
          "BCB",
          "PTH",
          "TTF-TDZ"
        ],
        "top3_candidate_names": [
          "BCB",
          "PTH",
          "TTF-TDZ"
        ],
        "top3_sims": [
          0.37878349003337675,
          0.33212071493693757,
          0.32025364541841295
        ],
        "gt_atom_count": 12,
        "pred_atom_count": 36,
        "pred_object_score": 0.3730566595045347,
        "pred_object_3d_score": 0.6220930409056895,
        "pred_object_count_mae": 24.0,
        "pred_object_type_acc": 0.75,
        "pred_object_macro_f1": 0.09375000000000001,
        "pred_object_hetero_f1": 0.0,
        "pred_object_edge_f1": 0.380952380952381,
        "pred_object_edge_f1_robust": 0.0,
        "pred_object_match_coverage_robust": 0.08333333333333333,
        "pred_object_heavy_rmsd": 0.1714366227388382,
        "pred_object_z_mae": 0.00031355072860606015,
        "mean_center_score": 0.8123236662811704,
        "figure_path": "/root/autodl-tmp/micro/experiments/v20_object_joint_medium10_sup03_real_afm_expanded/figures/inverted/edafm_BCB_Xe_exp.png",
        "compar_figure_path": "/root/autodl-tmp/micro/experiments/v20_object_joint_medium10_sup03_real_afm_expanded/comparisons/inverted/edafm_BCB_Xe_exp.png"
      },
      {
        "case_id": "edafm_PTCDA_CO_exp",
        "molecule_name": "PTCDA",
        "molecule_label": "PTCDA",
        "tip": "CO",
        "contrast_variant": "inverted",
        "gt_structure_compatible": true,
        "gt_rank": 3,
        "reciprocal_rank": 0.3333333333333333,
        "top1_hit": false,
        "top3_hit": true,
        "top5_hit": true,
        "top1_label": "PTH",
        "top1_candidate_name": "PTH",
        "top1_sim": 0.486684336690239,
        "top3_labels": [
          "PTH",
          "BCB",
          "PTCDA"
        ],
        "top3_candidate_names": [
          "PTH",
          "BCB",
          "PTCDA"
        ],
        "top3_sims": [
          0.486684336690239,
          0.4710194791303423,
          0.4687362312388059
        ],
        "gt_atom_count": 38,
        "pred_atom_count": 48,
        "pred_object_score": 0.5256415253695432,
        "pred_object_3d_score": 0.6396935723503078,
        "pred_object_count_mae": 10.0,
        "pred_object_type_acc": 0.6052631578947368,
        "pred_object_macro_f1": 0.1775,
        "pred_object_hetero_f1": 0.4615384615384615,
        "pred_object_edge_f1": 0.5060240963855421,
        "pred_object_edge_f1_robust": 0.0,
        "pred_object_match_coverage_robust": 0.10526315789473684,
        "pred_object_heavy_rmsd": 0.18751655519008636,
        "pred_object_z_mae": 0.09144887328147888,
        "mean_center_score": 0.9928029477596283,
        "figure_path": "/root/autodl-tmp/micro/experiments/v20_object_joint_medium10_sup03_real_afm_expanded/figures/inverted/edafm_PTCDA_CO_exp.png",
        "compar_figure_path": "/root/autodl-tmp/micro/experiments/v20_object_joint_medium10_sup03_real_afm_expanded/comparisons/inverted/edafm_PTCDA_CO_exp.png"
      },
      {
        "case_id": "edafm_PTCDA_Xe_exp",
        "molecule_name": "PTCDA",
        "molecule_label": "PTCDA",
        "tip": "Xe",
        "contrast_variant": "inverted",
        "gt_structure_compatible": true,
        "gt_rank": 5,
        "reciprocal_rank": 0.2,
        "top1_hit": false,
        "top3_hit": false,
        "top5_hit": true,
        "top1_label": "BCB",
        "top1_candidate_name": "BCB",
        "top1_sim": 0.5158401365507217,
        "top3_labels": [
          "BCB",
          "PTH",
          "TTF-TDZ"
        ],
        "top3_candidate_names": [
          "BCB",
          "PTH",
          "TTF-TDZ"
        ],
        "top3_sims": [
          0.5158401365507217,
          0.5152049743430709,
          0.5047113372599973
        ],
        "gt_atom_count": 38,
        "pred_atom_count": 48,
        "pred_object_score": 0.4697119173105321,
        "pred_object_3d_score": 0.6773920745129861,
        "pred_object_count_mae": 10.0,
        "pred_object_type_acc": 0.5789473684210527,
        "pred_object_macro_f1": 0.10784313725490197,
        "pred_object_hetero_f1": 0.2,
        "pred_object_edge_f1": 0.5252525252525252,
        "pred_object_edge_f1_robust": 0.4,
        "pred_object_match_coverage_robust": 0.15789473684210525,
        "pred_object_heavy_rmsd": 0.13976474106311798,
        "pred_object_z_mae": 0.13622888922691345,
        "mean_center_score": 0.9921188540756702,
        "figure_path": "/root/autodl-tmp/micro/experiments/v20_object_joint_medium10_sup03_real_afm_expanded/figures/inverted/edafm_PTCDA_Xe_exp.png",
        "compar_figure_path": "/root/autodl-tmp/micro/experiments/v20_object_joint_medium10_sup03_real_afm_expanded/comparisons/inverted/edafm_PTCDA_Xe_exp.png"
      },
      {
        "case_id": "edafm_Water_CO_exp",
        "molecule_name": "Water",
        "molecule_label": "Water",
        "tip": "CO",
        "contrast_variant": "inverted",
        "gt_structure_compatible": false,
        "gt_rank": 7,
        "reciprocal_rank": 0.14285714285714285,
        "top1_hit": false,
        "top3_hit": false,
        "top5_hit": false,
        "top1_label": "BCB",
        "top1_candidate_name": "BCB",
        "top1_sim": 0.38901102367569423,
        "top3_labels": [
          "BCB",
          "PTCDA",
          "camphor"
        ],
        "top3_candidate_names": [
          "BCB",
          "PTCDA",
          "camphor_A3"
        ],
        "top3_sims": [
          0.38901102367569423,
          0.3764870830176327,
          0.3268979144943936
        ],
        "gt_atom_count": null,
        "pred_atom_count": 48,
        "pred_object_score": null,
        "pred_object_3d_score": null,
        "pred_object_count_mae": null,
        "pred_object_type_acc": null,
        "pred_object_macro_f1": null,
        "pred_object_hetero_f1": null,
        "pred_object_edge_f1": null,
        "pred_object_edge_f1_robust": null,
        "pred_object_match_coverage_robust": null,
        "pred_object_heavy_rmsd": null,
        "pred_object_z_mae": null,
        "mean_center_score": 0.661853284885486,
        "figure_path": "/root/autodl-tmp/micro/experiments/v20_object_joint_medium10_sup03_real_afm_expanded/figures/inverted/edafm_Water_CO_exp.png",
        "compar_figure_path": "/root/autodl-tmp/micro/experiments/v20_object_joint_medium10_sup03_real_afm_expanded/comparisons/inverted/edafm_Water_CO_exp.png"
      },
      {
        "case_id": "edafm_Water_Xe_exp",
        "molecule_name": "Water",
        "molecule_label": "Water",
        "tip": "Xe",
        "contrast_variant": "inverted",
        "gt_structure_compatible": false,
        "gt_rank": 2,
        "reciprocal_rank": 0.5,
        "top1_hit": false,
        "top3_hit": true,
        "top5_hit": true,
        "top1_label": "PTCDA",
        "top1_candidate_name": "PTCDA",
        "top1_sim": 0.3570654143445111,
        "top3_labels": [
          "PTCDA",
          "Water",
          "BCB"
        ],
        "top3_candidate_names": [
          "PTCDA",
          "Water",
          "BCB"
        ],
        "top3_sims": [
          0.3570654143445111,
          0.34965152030873864,
          0.3012594665740068
        ],
        "gt_atom_count": null,
        "pred_atom_count": 10,
        "pred_object_score": null,
        "pred_object_3d_score": null,
        "pred_object_count_mae": null,
        "pred_object_type_acc": null,
        "pred_object_macro_f1": null,
        "pred_object_hetero_f1": null,
        "pred_object_edge_f1": null,
        "pred_object_edge_f1_robust": null,
        "pred_object_match_coverage_robust": null,
        "pred_object_heavy_rmsd": null,
        "pred_object_z_mae": null,
        "mean_center_score": 0.8449269890785217,
        "figure_path": "/root/autodl-tmp/micro/experiments/v20_object_joint_medium10_sup03_real_afm_expanded/figures/inverted/edafm_Water_Xe_exp.png",
        "compar_figure_path": "/root/autodl-tmp/micro/experiments/v20_object_joint_medium10_sup03_real_afm_expanded/comparisons/inverted/edafm_Water_Xe_exp.png"
      },
      {
        "case_id": "camphor_exp_1",
        "molecule_name": "camphor",
        "molecule_label": "camphor",
        "tip": "unknown",
        "contrast_variant": "inverted",
        "gt_structure_compatible": false,
        "gt_rank": 2,
        "reciprocal_rank": 0.5,
        "top1_hit": false,
        "top3_hit": true,
        "top5_hit": true,
        "top1_label": "BCB",
        "top1_candidate_name": "BCB",
        "top1_sim": 0.45245168888795945,
        "top3_labels": [
          "BCB",
          "camphor",
          "TTF-TDZ"
        ],
        "top3_candidate_names": [
          "BCB",
          "camphor_A2",
          "TTF-TDZ"
        ],
        "top3_sims": [
          0.45245168888795945,
          0.3619227162652491,
          0.24447690699948646
        ],
        "gt_atom_count": null,
        "pred_atom_count": 48,
        "pred_object_score": null,
        "pred_object_3d_score": null,
        "pred_object_count_mae": null,
        "pred_object_type_acc": null,
        "pred_object_macro_f1": null,
        "pred_object_hetero_f1": null,
        "pred_object_edge_f1": null,
        "pred_object_edge_f1_robust": null,
        "pred_object_match_coverage_robust": null,
        "pred_object_heavy_rmsd": null,
        "pred_object_z_mae": null,
        "mean_center_score": 0.3015132909834695,
        "figure_path": "/root/autodl-tmp/micro/experiments/v20_object_joint_medium10_sup03_real_afm_expanded/figures/inverted/camphor_exp_1.png",
        "compar_figure_path": "/root/autodl-tmp/micro/experiments/v20_object_joint_medium10_sup03_real_afm_expanded/comparisons/inverted/camphor_exp_1.png"
      },
      {
        "case_id": "camphor_exp_3",
        "molecule_name": "camphor",
        "molecule_label": "camphor",
        "tip": "unknown",
        "contrast_variant": "inverted",
        "gt_structure_compatible": false,
        "gt_rank": 6,
        "reciprocal_rank": 0.16666666666666666,
        "top1_hit": false,
        "top3_hit": false,
        "top5_hit": false,
        "top1_label": "BCB",
        "top1_candidate_name": "BCB",
        "top1_sim": 0.5933413027695247,
        "top3_labels": [
          "BCB",
          "PTCDA",
          "TTF-TDZ"
        ],
        "top3_candidate_names": [
          "BCB",
          "PTCDA",
          "TTF-TDZ"
        ],
        "top3_sims": [
          0.5933413027695247,
          0.5240420502666148,
          0.4945050208676037
        ],
        "gt_atom_count": null,
        "pred_atom_count": 48,
        "pred_object_score": null,
        "pred_object_3d_score": null,
        "pred_object_count_mae": null,
        "pred_object_type_acc": null,
        "pred_object_macro_f1": null,
        "pred_object_hetero_f1": null,
        "pred_object_edge_f1": null,
        "pred_object_edge_f1_robust": null,
        "pred_object_match_coverage_robust": null,
        "pred_object_heavy_rmsd": null,
        "pred_object_z_mae": null,
        "mean_center_score": 0.8223398455884308,
        "figure_path": "/root/autodl-tmp/micro/experiments/v20_object_joint_medium10_sup03_real_afm_expanded/figures/inverted/camphor_exp_3.png",
        "compar_figure_path": "/root/autodl-tmp/micro/experiments/v20_object_joint_medium10_sup03_real_afm_expanded/comparisons/inverted/camphor_exp_3.png"
      },
      {
        "case_id": "camphor_exp_4",
        "molecule_name": "camphor",
        "molecule_label": "camphor",
        "tip": "unknown",
        "contrast_variant": "inverted",
        "gt_structure_compatible": false,
        "gt_rank": 5,
        "reciprocal_rank": 0.2,
        "top1_hit": false,
        "top3_hit": false,
        "top5_hit": true,
        "top1_label": "BCB",
        "top1_candidate_name": "BCB",
        "top1_sim": 0.5430910293854676,
        "top3_labels": [
          "BCB",
          "TTF-TDZ",
          "PTH"
        ],
        "top3_candidate_names": [
          "BCB",
          "TTF-TDZ",
          "PTH"
        ],
        "top3_sims": [
          0.5430910293854676,
          0.4611015175810511,
          0.4348122887030504
        ],
        "gt_atom_count": null,
        "pred_atom_count": 48,
        "pred_object_score": null,
        "pred_object_3d_score": null,
        "pred_object_count_mae": null,
        "pred_object_type_acc": null,
        "pred_object_macro_f1": null,
        "pred_object_hetero_f1": null,
        "pred_object_edge_f1": null,
        "pred_object_edge_f1_robust": null,
        "pred_object_match_coverage_robust": null,
        "pred_object_heavy_rmsd": null,
        "pred_object_z_mae": null,
        "mean_center_score": 0.42205193588597467,
        "figure_path": "/root/autodl-tmp/micro/experiments/v20_object_joint_medium10_sup03_real_afm_expanded/figures/inverted/camphor_exp_4.png",
        "compar_figure_path": "/root/autodl-tmp/micro/experiments/v20_object_joint_medium10_sup03_real_afm_expanded/comparisons/inverted/camphor_exp_4.png"
      },
      {
        "case_id": "camphor_exp_6",
        "molecule_name": "camphor",
        "molecule_label": "camphor",
        "tip": "unknown",
        "contrast_variant": "inverted",
        "gt_structure_compatible": false,
        "gt_rank": 4,
        "reciprocal_rank": 0.25,
        "top1_hit": false,
        "top3_hit": false,
        "top5_hit": true,
        "top1_label": "BCB",
        "top1_candidate_name": "BCB",
        "top1_sim": 0.5582120064934627,
        "top3_labels": [
          "BCB",
          "PTH",
          "TTF-TDZ"
        ],
        "top3_candidate_names": [
          "BCB",
          "PTH",
          "TTF-TDZ"
        ],
        "top3_sims": [
          0.5582120064934627,
          0.5218739769237355,
          0.49012258472602777
        ],
        "gt_atom_count": null,
        "pred_atom_count": 48,
        "pred_object_score": null,
        "pred_object_3d_score": null,
        "pred_object_count_mae": null,
        "pred_object_type_acc": null,
        "pred_object_macro_f1": null,
        "pred_object_hetero_f1": null,
        "pred_object_edge_f1": null,
        "pred_object_edge_f1_robust": null,
        "pred_object_match_coverage_robust": null,
        "pred_object_heavy_rmsd": null,
        "pred_object_z_mae": null,
        "mean_center_score": 0.6092939189014336,
        "figure_path": "/root/autodl-tmp/micro/experiments/v20_object_joint_medium10_sup03_real_afm_expanded/figures/inverted/camphor_exp_6.png",
        "compar_figure_path": "/root/autodl-tmp/micro/experiments/v20_object_joint_medium10_sup03_real_afm_expanded/comparisons/inverted/camphor_exp_6.png"
      },
      {
        "case_id": "camphor_exp_7",
        "molecule_name": "camphor",
        "molecule_label": "camphor",
        "tip": "unknown",
        "contrast_variant": "inverted",
        "gt_structure_compatible": false,
        "gt_rank": 6,
        "reciprocal_rank": 0.16666666666666666,
        "top1_hit": false,
        "top3_hit": false,
        "top5_hit": false,
        "top1_label": "BCB",
        "top1_candidate_name": "BCB",
        "top1_sim": 0.5857780342573647,
        "top3_labels": [
          "BCB",
          "PTH",
          "NCM"
        ],
        "top3_candidate_names": [
          "BCB",
          "PTH",
          "NCM"
        ],
        "top3_sims": [
          0.5857780342573647,
          0.5658921513183901,
          0.5529781948641522
        ],
        "gt_atom_count": null,
        "pred_atom_count": 48,
        "pred_object_score": null,
        "pred_object_3d_score": null,
        "pred_object_count_mae": null,
        "pred_object_type_acc": null,
        "pred_object_macro_f1": null,
        "pred_object_hetero_f1": null,
        "pred_object_edge_f1": null,
        "pred_object_edge_f1_robust": null,
        "pred_object_match_coverage_robust": null,
        "pred_object_heavy_rmsd": null,
        "pred_object_z_mae": null,
        "mean_center_score": 0.8060025398929914,
        "figure_path": "/root/autodl-tmp/micro/experiments/v20_object_joint_medium10_sup03_real_afm_expanded/figures/inverted/camphor_exp_7.png",
        "compar_figure_path": "/root/autodl-tmp/micro/experiments/v20_object_joint_medium10_sup03_real_afm_expanded/comparisons/inverted/camphor_exp_7.png"
      }
    ]
  }
}